agal/__init__.py
agal/cli.py
agal/constant.py
agal/hamlet.json
agal/message_crypt.py
agal/sender.py
agal/server.py
agal/static/asset-manifest.json
agal/static/favicon.ico
agal/static/index.html
agal/static/static/css/main.d54db86d.css
agal/static/static/css/main.d54db86d.css.map
agal/static/static/js/787.d1d4a2c2.chunk.js
agal/static/static/js/787.d1d4a2c2.chunk.js.map
agal/static/static/js/main.5cc894a5.js
agal/static/static/js/main.5cc894a5.js.LICENSE.txt
agal/static/static/js/main.5cc894a5.js.map
agal/tail.py
agal/util.py
agal-0.0.6.dist-info/entry_points.txt
agal-0.0.6.dist-info/WHEEL
agal-0.0.6.dist-info/METADATA
agal-0.0.6.dist-info/RECORD
