Metadata-Version: 2.1
Name: agal
Version: 0.0.6
Summary: 
Home-page: https://github.com/gzttech/agal
License: MIT
Author: Gongziting Tech Ltd.
Requires-Python: >=3.7,<4.0
Classifier: License :: OSI Approved :: MIT License
Classifier: Programming Language :: Python :: 3
Classifier: Programming Language :: Python :: 3.7
Classifier: Programming Language :: Python :: 3.8
Classifier: Programming Language :: Python :: 3.9
Classifier: Programming Language :: Python :: 3.10
Classifier: Programming Language :: Python :: 3.11
Requires-Dist: cryptography (>=3.4.7,<4.0.0)
Requires-Dist: fire (>=0.3.1,<0.4.0)
Requires-Dist: websockets (>=10.1,<11.0)
